lmanage/.vimspector.json
lmanage/__init__.py
lmanage/capturator/__init__.py
lmanage/capturator/content_capturation/__init__.py
lmanage/capturator/content_capturation/board_capture.py
lmanage/capturator/content_capturation/dashboard_capture.py
lmanage/capturator/content_capturation/look_capture.py
lmanage/capturator/folder_capturation/__init__.py
lmanage/capturator/folder_capturation/create_folder_yaml_structure.py
lmanage/capturator/folder_capturation/folder_config.py
lmanage/capturator/looker_api_reader.py
lmanage/capturator/looker_config_saver.py
lmanage/capturator/user_attribute_capturation/__init__.py
lmanage/capturator/user_attribute_capturation/capture_ua_permissions.py
lmanage/capturator/user_group_capturation/__init__.py
lmanage/capturator/user_group_capturation/group_config.py
lmanage/capturator/user_group_capturation/role_config.py
lmanage/capturator/user_group_capturation/user_permission.py
lmanage/cli.py
lmanage/configurator/.vimspector.json
lmanage/configurator/__init__.py
lmanage/configurator/content_configuration/__init__.py
lmanage/configurator/content_configuration/clean_instance_content.py
lmanage/configurator/content_configuration/create_boards.py
lmanage/configurator/content_configuration/create_dashboards.py
lmanage/configurator/content_configuration/create_looks.py
lmanage/configurator/create_object.py
lmanage/configurator/folder_configuration/__init__.py
lmanage/configurator/folder_configuration/create_and_provision_instance_folders.py
lmanage/configurator/folder_configuration/create_instance_folders.py
lmanage/configurator/folder_configuration/folder_config.py
lmanage/configurator/instance_configuration_settings/fullinstance.yaml
lmanage/configurator/looker_config_reader.py
lmanage/configurator/looker_provisioner.py
lmanage/configurator/user_attribute_configuration/__init__.py
lmanage/configurator/user_attribute_configuration/create_and_assign_user_attributes.py
lmanage/configurator/user_group_configuration/__init__.py
lmanage-0.3.36.dist-info/LICENSE
lmanage-0.3.36.dist-info/METADATA
lmanage-0.3.36.dist-info/WHEEL
lmanage-0.3.36.dist-info/entry_points.txt
lmanage-0.3.36.dist-info/RECORD
