Metadata-Version: 2.1
Name: lmanage
Version: 0.3.36
Summary: LManage is a collection of useful tools for Looker admins to help curate and cleanup content and it's associated source LookML.
Home-page: https://github.com/looker-open-source/lmanage
Keywords: keyword,another_keyword
Author: hselbie
Author-email: hselbie@gmail.com
Requires-Python: >=3.8,<3.12
Classifier: Programming Language :: Python :: 3
Classifier: Programming Language :: Python :: 3.8
Classifier: Programming Language :: Python :: 3.9
Classifier: Programming Language :: Python :: 3.10
Classifier: Programming Language :: Python :: 3.11
Requires-Dist: click (>=8.1.3,<9.0.0)
Requires-Dist: looker-sdk (>=23.8.1,<24.0.0)
Requires-Dist: poetry (>=1.4.2,<2.0.0)
Requires-Dist: rich (>=13.4.2,<14.0.0)
Requires-Dist: ruamel-yaml (>=0.17.32,<0.18.0)
Requires-Dist: tenacity (>=8.2.2,<9.0.0)
Requires-Dist: tqdm (>=4.65.0,<5.0.0)
Requires-Dist: yaspin (>=2.3.0,<3.0.0)
Project-URL: Repository, https://github.com/looker-open-source/lmanage
